{
  "version": "1",
  "metadata": {
    "marimo_version": "0.23.1",
    "script_metadata_hash": null
  },
  "cells": [
    {
      "id": "Hbol",
      "code_hash": "387b9c44183264a09c245ac3755ad0f7",
      "outputs": [
        {
          "type": "data",
          "data": {
            "text/plain": ""
          }
        }
      ],
      "console": []
    },
    {
      "id": "MJUe",
      "code_hash": "36bf0cb729181ebb14219a66442508e4",
      "outputs": [
        {
          "type": "data",
          "data": {
            "text/plain": ""
          }
        }
      ],
      "console": []
    },
    {
      "id": "vblA",
      "code_hash": "71fb25557a33ffcb2ee1bd1fa4b6c9b9",
      "outputs": [
        {
          "type": "data",
          "data": {
            "text/plain": ""
          }
        }
      ],
      "console": []
    },
    {
      "id": "bkHC",
      "code_hash": "82ae6ead084d0078d66bd7069a137de1",
      "outputs": [
        {
          "type": "data",
          "data": {
            "text/plain": ""
          }
        }
      ],
      "console": []
    },
    {
      "id": "lEQa",
      "code_hash": "16cfe386e6685e045a42c092f1ba81f4",
      "outputs": [
        {
          "type": "data",
          "data": {
            "text/plain": ""
          }
        }
      ],
      "console": []
    },
    {
      "id": "Xref",
      "code_hash": "b2c96831d1cc9b3e097eeed3c7d9ecd9",
      "outputs": [],
      "console": []
    }
  ]
}